QvQChat/Core.py
QvQChat/__init__.py
QvQChat/active_mode_manager.py
QvQChat/ai_client.py
QvQChat/commands.py
QvQChat/config.py
QvQChat/handler.py
QvQChat/intent.py
QvQChat/memory.py
QvQChat/reply_judge.py
QvQChat/session_manager.py
QvQChat/state.py
QvQChat/utils.py
erispulse_qvqchat-2.3.1.dist-info/licenses/LICENSE
erispulse_qvqchat-2.3.1.dist-info/METADATA
erispulse_qvqchat-2.3.1.dist-info/WHEEL
erispulse_qvqchat-2.3.1.dist-info/entry_points.txt
erispulse_qvqchat-2.3.1.dist-info/top_level.txt
erispulse_qvqchat-2.3.1.dist-info/RECORD
