Metadata-Version: 2.4
Name: ErisPulse-QvQChat
Version: 2.3.1
Summary: ErisPulse QvQChat 智能对话模块 - 多AI协同智能体
Author-email: wsu2059q <wsu2059@qq.com>
License: MIT License
Project-URL: homepage, https://github.com/wsu2059q/ErisPulse-AIChat
Requires-Python: >=3.10
License-File: LICENSE
Requires-Dist: openai>=1.0.0
Requires-Dist: ErisPulse-HelpModule
Dynamic: license-file
